polars_geo_tools-0.2.1.dist-info/METADATA
polars_geo_tools-0.2.1.dist-info/WHEEL
polars_geo_tools.libs/libsqlite3-91918ceb.so.0
polars_geo_tools/s2/s2_api.py
polars_geo_tools/s2/__init__.py
polars_geo_tools/__init__.py
polars_geo_tools/utils.py
polars_geo_tools/h3/__init__.py
polars_geo_tools/h3/h3_api.py
polars_geo_tools/transformer/__init__.py
polars_geo_tools/transformer/transform.py
polars_geo_tools/polars_geo_tools.abi3.so
polars_geo_tools-0.2.1.dist-info/RECORD
